helloworld90210/__init__.py
helloworld90210/main.py
helloworld90210-0.0.3.dist-info/METADATA
helloworld90210-0.0.3.dist-info/WHEEL
helloworld90210-0.0.3.dist-info/top_level.txt
helloworld90210-0.0.3.dist-info/RECORD
