Metadata-Version: 2.1
Name: helloworld90210
Version: 0.0.3
Summary: SMDAPI by Arun microeletronics LTD
Author: Arun Microeletronics LTD
Author-email: ollie.sims@arunmicro.com
Project-URL: Arun Microeletronics LTD WEBSITE, https://arunmicro.com/
Classifier: Programming Language :: Python :: 3
Classifier: License :: OSI Approved :: MIT License
Classifier: Operating System :: OS Independent
Requires-Python: >=3.7
